Workbook

Sheet Inventario
A1: CONTROL DE INVENTARIO Y FACTURACIÓN - NEMET
A2: SKU | B2: Descripcion | C2: Presentacion | D2: StockMinimo | E2: StockInicial | F2: Entradas | G2: Salidas | H2: StockActual | I2: AlertaStock | J2: PrecioCompra | K2: PrecioBaseSinIVA | L2: IVA 16% | M2: PrecioPublicoIVA | N2: ValorInventario | O2: Línea
A3: EDT 01 | B3: EPO-DEEP TRANSPARENTE | C3: 1.420 kg | D3: 5 | E3: 0 | F3: 0 | G3: 0 | H3: 0 | I3: ⚠️ REABASTECER | J3: 655.87 | K3: 685.34483 | L3: 109.65517 | M3: 795 | N3: 0 | O3: Resina
A4: EDT 02 | B4: EPO-DEEP TRANSPARENTE | C4: 4.260 kg | D4: 5 | E4: 0 | F4: 0 | G4: 0 | H4: 0 | I4: ⚠️ REABASTECER | J4: 1967.61 | K4: 2056.8966 | L4: 329.10345 | M4: 2386 | N4: 0 | O4: Resina
A5: EDT 03 | B5: EPO-DEEP TRANSPARENTE | C5: 7.100 kg | D5: 5 | E5: 0 | F5: 0 | G5: 0 | H5: 0 | I5: ⚠️ REABASTECER | J5: 3015.44 | K5: 3182.7586 | L5: 509.24138 | M5: 3692 | N5: 0 | O5: Resina
A6: EDT 04 | B6: EPO-DEEP TRANSPARENTE | C6: 17.040 kg | D6: 5 | E6: 0 | F6: 0 | G6: 0 | H6: 0 | I6: ⚠️ REABASTECER | J6: 6635.89 | K6: 7344.8276 | L6: 1175.1724 | M6: 8520 | N6: 0 | O6: Resina
A7: EFT 01 | B7: EPO-FAST (A Y B) TRANSPARENTE | C7: 2 kg | D7: 5 | E7: 0 | F7: 0 | G7: 0 | H7: 0 | I7: ⚠️ REABASTECER | J7: 784.48 | K7: 827.58621 | L7: 132.41379 | M7: 960 | N7: 0 | O7: Resina
A8: EFT 02 | B8: EPO-FAST (A Y B) TRANSPARENTE | C8: 6 kg | D8: 5 | E8: 0 | F8: 0 | G8: 0 | H8: 0 | I8: ⚠️ REABASTECER | J8: 2241.3 | K8: 2379.3103 | L8: 380.68966 | M8: 2760 | N8: 0 | O8: Resina
A9: EFT 03 | B9: EPO-FAST (A Y B) TRANSPARENTE | C9: 10 kg | D9: 5 | E9: 0 | F9: 0 | G9: 0 | H9: 0 | I9: ⚠️ REABASTECER | J9: 3557.7 | K9: 3793.1034 | L9: 606.89655 | M9: 4400 | N9: 0 | O9: Resina
A10: EFT 04 | B10: EPO-FAST (A Y B) TRANSPARENTE | C10: 19 kg | D10: 5 | E10: 0 | F10: 0 | G10: 0 | H10: 0 | I10: ⚠️ REABASTECER | J10: 6186.02 | K10: 6879.3103 | L10: 1100.6897 | M10: 7980 | N10: 0 | O10: Resina
A11: EPT 01 | B11: EPOXY PISOS (A Y B) TRANSPARENTE | C11: 1.5 kg | D11: 5 | E11: 0 | F11: 0 | G11: 0 | H11: 0 | I11: ⚠️ REABASTECER | J11: 542.13 | K11: 620.68966 | L11: 99.310345 | M11: 720 | N11: 0 | O11: Resina
A12: EPT 02 | B12: EPOXY PISOS (A Y B) TRANSPARENTE | C12: 3 kg | D12: 5 | E12: 0 | F12: 0 | G12: 0 | H12: 0 | I12: ⚠️ REABASTECER | J12: 1084.26 | K12: 1241.3793 | L12: 198.62069 | M12: 1440 | N12: 0 | O12: Resina
A13: EPT 03 | B13: EPOXY PISOS (A Y B) TRANSPARENTE | C13: 6 kg | D13: 5 | E13: 0 | F13: 0 | G13: 0 | H13: 0 | I13: ⚠️ REABASTECER | J13: 2076.12 | K13: 2379.3103 | L13: 380.68966 | M13: 2760 | N13: 0 | O13: Resina
A14: EPT 04 | B14: EPOXY PISOS (A Y B) TRANSPARENTE | C14: 10 kg | D14: 5 | E14: 0 | F14: 0 | G14: 0 | H14: 0 | I14: ⚠️ REABASTECER | J14: 3329.5 | K14: 3793.1034 | L14: 606.89655 | M14: 4400 | N14: 0 | O14: Resina
... A90: ESP 01 | B90: EPOXY SPIKES PREMIUM | C90: 1 Pz | D90: 5 | E90: 0 | F90: 0 | G90: 0 | H90: 0 | I90: ⚠️ REABASTECER | J90: 2373.11 | K90: 2153.4483 | L90: 344.55172 | M90: 2498 | N90: 0 | O90: Herramienta

Sheet Cotizador_Rendimientos
A1: COTIZADOR Y CALCULADORA DE RENDIMIENTOS - NEMET
A3: INSTRUCCIONES: Ingrese en la tabla de abajo el producto que desea el cliente, los metros cuadrados (m²) y el espesor deseado (mm). El sistema calculará automáticamente la presentación ideal y el costo total.
A5: --- DATOS DE COTIZACIÓN PARA EL CLIENTE ---
A6: Producto Seleccionado | B6: EPOXY PISOS (A Y B) TRANSPARENTE
A7: Área del Espacio (m²) | B7: 16
A8: Espesor Requerido (mm) | B8: 1
A9: Rendimiento Teórico (kg/m² por mm) | B9: =VLOOKUP(B6, Cat_Productos!$A$2:$G$58, 5, FALSE)
A11: TOTAL DE MATERIAL NECESARIO (kg) | B11: =B7*B8*B9 | C11: kg
A13: --- PRESENTACIONES DISPONIBLES Y RECOMENDACIÓN DE VENTA ---
A14: Presentación (kg) | B14: Precio Público (IVA Inc.) | C14: Costo por kg | D14: ¿Cuántas unidades incluir? | E14: Kg aportados | F14: Subtotal ($)
A15: 1.5 | B15: =IFERROR(SUMIFS(Cat_Productos!$D$2:$D$58, Cat_Productos!$A$2:$A$58, $B$6, Cat_Productos!$C$2:$C$58, A15), 0) | C15: =IFERROR(B15/A15, 0) | D15: 0 | E15: =A15*D15 | F15: =B15*D15
A16: 3 | B16: =IFERROR(SUMIFS(Cat_Productos!$D$2:$D$58, Cat_Productos!$A$2:$A$58, $B$6, Cat_Productos!$C$2:$C$58, A16), 0) | C16: =IFERROR(B16/A16, 0) | D16: 0 | E16: =A16*D16 | F16: =B16*D16
A17: 6 | B17: =IFERROR(SUMIFS(Cat_Productos!$D$2:$D$58, Cat_Productos!$A$2:$A$58, $B$6, Cat_Productos!$C$2:$C$58, A17), 0) | C17: =IFERROR(B17/A17, 0) | D17: 0 | E17: =A17*D17 | F17: =B17*D17
A18: 10 | B18: =IFERROR(SUMIFS(Cat_Productos!$D$2:$D$58, Cat_Productos!$A$2:$A$58, $B$6, Cat_Productos!$C$2:$C$58, A18), 0) | C18: =IFERROR(B18/A18, 0) | D18: 0 | E18: =A18*D18 | F18: =B18*D18
A19: 15 | B19: =IFERROR(SUMIFS(Cat_Productos!$D$2:$D$58, Cat_Productos!$A$2:$A$58, $B$6, Cat_Productos!$C$2:$C$58, A19), 0) | C19: =IFERROR(B19/A19, 0) | D19: 0 | E19: =A19*D19 | F19: =B19*D19
A20: 20 | B20: =IFERROR(SUMIFS(Cat_Productos!$D$2:$D$58, Cat_Productos!$A$2:$A$58, $B$6, Cat_Productos!$C$2:$C$58, A20), 0) | C20: =IFERROR(B20/A20, 0) | D20: =ROUNDUP(B11/A20, 0) | E20: =A20*D20 | F20: =B20*D20
A22: TOTAL KILOGRAMOS CUBIERTOS | B22: =SUM(E15:E20) | C22: kg (Debe cubrir al menos 19.2 kg)
A23: TOTAL A PAGAR POR EL CLIENTE (IVA Inc.) | B23: =SUM(F15:F20) | C23: $ MXN
A25: --- PROPORCIÓN DE MEZCLA (PARTE A Y PARTE B) ---
A26: Componente | B26: Proporción / Relación | C26: Kg a mezclar según total requerido
A27: Parte A (Resina) | B27: 100 partes | C27: =B11 * (100 / (100 + IFERROR(SUMIFS(Cat_Productos!$G$2:$G$58, Cat_Productos!$A$2:$A$58, $B$6), 50))) | D27: kg
A28: Parte B (Catalizador) | B28: 50 partes | C28: =B11 - C27 | D28: kg

Sheet Cat_Productos
A1: Producto | B1: Unnamed: 1 | C1: Presentacion | D1: PrecioPublico | E1: Rendimiento | F1: Prop_A | G1: Prop_B | H1: Dosis_g_m2 | I1: Fuente_Dosis
A2: EPOXY PISOS (A Y B) TRANSPARENTE | C2: 1.5 | D2: 720 | E2: 1.2 | F2: 100 | G2: 50
A3: EPOXY PISOS (A Y B) TRANSPARENTE | C3: 3 | D3: 1440 | E3: 1.2 | F3: 100 | G3: 50
A4: EPOXY PISOS (A Y B) TRANSPARENTE | C4: 6 | D4: 2760 | E4: 1.2 | F4: 100 | G4: 50
A5: EPOXY PISOS (A Y B) TRANSPARENTE | C5: 10 | D5: 4400 | E5: 1.2 | F5: 100 | G5: 50
A6: EPOXY PISOS (A Y B) TRANSPARENTE | C6: 15 | D6: 6300 | E6: 1.2 | F6: 100 | G6: 50
A7: EPOXY PISOS (A Y B) TRANSPARENTE | C7: 20 | D7: 8000 | E7: 1.2 | F7: 100 | G7: 50
A8: EPO-FAST (A Y B) TRANSPARENTE | C8: 2 | D8: 960 | E8: 1 | F8: 100 | G8: 84
A9: EPO-FAST (A Y B) TRANSPARENTE | C9: 6 | D9: 2760 | E9: 1 | F9: 100 | G9: 84
A10: EPO-FAST (A Y B) TRANSPARENTE | C10: 10 | D10: 4400 | E10: 1 | F10: 100 | G10: 84
A11: EPO-FAST (A Y B) TRANSPARENTE | C11: 19 | D11: 7980 | E11: 1 | F11: 100 | G11: 84
A12: EPO-DEEP TRANSPARENTE | C12: 1.42 | D12: 795 | E12: 1.07 | F12: 100 | G12: 42
A13: EPO-DEEP TRANSPARENTE | C13: 4.26 | D13: 2386 | E13: 1.07 | F13: 100 | G13: 42
... A26: POLIURETANO (A Y B) TRANSPARENTE | C26: 20 | D26: 8250 | E26: 0.1 | F26: 100 | G26: 50
A27: EPOXY PASTA COLORES SÓLIDOS | C27: 60 | D27: 75 | F27: 100 | G27: 0 | H27: 10 | I27: Manual NEMET: 10 g/m²
A28: EPOXY PASTA COLORES SÓLIDOS | C28: 100 | D28: 112 | F28: 100 | G28: 0 | H28: 10 | I28: Manual NEMET: 10 g/m²
A29: EPOXY PASTA COLORES SÓLIDOS | C29: 250 | D29: 270 | F29: 100 | G29: 0 | H29: 10 | I29: Manual NEMET: 10 g/m²
A30: EPOXY PASTA COLORES SÓLIDOS | C30: 500 | D30: 520 | F30: 100 | G30: 0 | H30: 10 | I30: Manual NEMET: 10 g/m²
A31: EPOXY PASTA COLORES SÓLIDOS | C31: 1 | D31: 840 | F31: 100 | G31: 0 | H31: 10 | I31: Manual NEMET: 10 g/m²
A32: EPOXY TINTA | C32: 20 | D32: 25 | F32: 100 | G32: 0 | H32: 60 | I32: Referencia de trabajo: ≈60 ml/m² (1 L ≈ 16 m²); ajustar si el manual la especifica
A33: EPOXY TINTA | C33: 60 | D33: 65 | F33: 100 | G33: 0 | H33: 60 | I33: Referencia de trabajo: ≈60 ml/m² (1 L ≈ 16 m²); ajustar si el manual la especifica
A34: EPOXY TINTA | C34: 100 | D34: 110 | F34: 100 | G34: 0 | H34: 60 | I34: Referencia de trabajo: ≈60 ml/m² (1 L ≈ 16 m²); ajustar si el manual la especifica
A35: EPOXY TINTA | C35: 250 | D35: 190 | F35: 100 | G35: 0 | H35: 60 | I35: Referencia de trabajo: ≈60 ml/m² (1 L ≈ 16 m²); ajustar si el manual la especifica
A36: EPOXY TINTA | C36: 500 | D36: 320 | F36: 100 | G36: 0 | H36: 60 | I36: Referencia de trabajo: ≈60 ml/m² (1 L ≈ 16 m²); ajustar si el manual la especifica
A37: EPOXY TINTA | C37: 1 | D37: 550 | F37: 100 | G37: 0 | H37: 60 | I37: Referencia de trabajo: ≈60 ml/m² (1 L ≈ 16 m²); ajustar si el manual la especifica
A38: PIGMENTOS FOTOLUMINISCENTES | C38: 20 | D38: 275 | F38: 100 | G38: 0 | H38: 10 | I38: Criterio NEMET para pigmentos en polvo (ajustable)
... A52: EPOXY-MICA (combinado) | C52: 1 | D52: 495 | F52: 100 | G52: 0 | H52: 8 | I52: Manual NEMET: 8 g/m²
A53: EPO-PAINT (A y B) | C53: 0 | D53: 0 | E53: 0.2 | F53: 100 | G53: 50 | I53: Criterio NEMET: ≈0.2 kg/m² por capa
A54: ARENA SILICA | C54: 0 | D54: 0 | F54: 100 | G54: 0 | H54: 2000 | I54: Criterio NEMET: arena sílica como carga ≈2 kg/m² (ajustable)
A55: CÁSCARA DE NARANJA | C55: 1 | D55: 580 | F55: 100 | G55: 0 | H55: 100 | I55: Criterio NEMET: texturizante al voleo ≈100 g/m² (ajustable)
A56: ESTUCO VENECIANO | C56: 1 | D56: 480 | E56: 1 | F56: 100 | G56: 0 | I56: Criterio NEMET: ≈1 L/m² por capa de 1 mm
A57: GRANO WALL | C57: 4 | D57: 1100 | E57: 1.5 | F57: 100 | G57: 0 | I57: Criterio NEMET: ≈1.5 L/m² por capa
A58: EPOXY CUARZO | C58: 1 | D58: 35 | F58: 100 | G58: 0 | H58: 2500 | I58: Criterio NEMET: cuarzo al voleo ≈2.5 kg/m² (ajustable)

Sheet Clientes
A1: Nombre | B1: Empresa | C1: Correo | D1: Teléfono | E1: Dirección
A2: Luis Manuel Merelles Lourido | B2: Nemet | C2: luismerelles@gmail.com

Sheet Historial_Cotizaciones
A1: Folio | B1: Fecha | C1: Cliente | D1: Detalle_Productos | E1: Total
A2: COT-2026-001 | B2: 2026-09-28 14:10:48 | C2: Luis Manuel Merelles Lourido | D2: 2x EPO-DEEP TRANSPARENTE (7.100 kg) [12.00 m² x 1 mm] | E2: 7110

Sheet Escalas_Precios_KG
A1: Producto_Proveedor | B1: Producto_NEMET | C1: Rango_Desde_Kg | D1: Rango_Hasta_Kg | E1: Costo_Compra_IVA_por_Kg | F1: Precio_Publico_por_Kg | G1: Margen_por_Kg | H1: Margen_Porcentaje_Sobre_Venta | I1: Margen_Markup_Sobre_Costo | J1: Rango_Texto_Original
A2: EPOXY PISOS | B2: EPOXY PISOS (A Y B) TRANSPARENTE | C2: 0 | D2: 5.999 | E2: 361.42 | F2: 480 | G2: 118.58 | H2: 24.704167 | I2: 32.809474 | J2: 0 - 5.999 kg
A3: EPOXY PISOS | B3: EPOXY PISOS (A Y B) TRANSPARENTE | C3: 6 | D3: 9.999 | E3: 346.02 | F3: 460 | G3: 113.98 | H3: 24.778261 | I3: 32.940292 | J3: 6 - 9.999 kg
A4: EPOXY PISOS | B4: EPOXY PISOS (A Y B) TRANSPARENTE | C4: 10 | D4: 14.999 | E4: 332.95 | F4: 440 | G4: 107.05 | H4: 24.329545 | I4: 32.151975 | J4: 10 - 14.999 kg
A5: EPOXY PISOS | B5: EPOXY PISOS (A Y B) TRANSPARENTE | C5: 15 | D5: 19.999 | E5: 316.8 | F5: 420 | G5: 103.2 | H5: 24.571429 | I5: 32.575758 | J5: 15 - 19.999 kg
A6: EPOXY PISOS | B6: EPOXY PISOS (A Y B) TRANSPARENTE | C6: 20 | E6: 301.45 | F6: 400 | G6: 98.55 | H6: 24.6375 | I6: 32.691989 | J6: + 20 kg
A7: EPOXY PRIMER | B7: EPOXY PRIMER (A Y B) TRANSPARENTE | C7: 0 | D7: 9.999 | E7: 397.99 | F7: 400 | G7: 2.01 | H7: 0.5025 | I7: 0.50503782 | J7: 0 - 9.999 kg
A8: EPOXY PRIMER | B8: EPOXY PRIMER (A Y B) TRANSPARENTE | C8: 10 | D8: 19.999 | E8: 292.7 | F8: 380 | G8: 87.3 | H8: 22.973684 | I8: 29.82576 | J8: 10 - 19.999 kg
A9: EPOXY PRIMER | B9: EPOXY PRIMER (A Y B) TRANSPARENTE | C9: 20 | E9: 276.35 | F9: 370 | G9: 93.65 | H9: 25.310811 | I9: 33.888185 | J9: + 20 kg
A10: CÁSCARA DE NARANJA | B10: CÁSCARA DE NARANJA | C10: 0 | D10: 3.999 | E10: 444.45 | F10: 580 | G10: 135.55 | H10: 23.37069 | I10: 30.498369 | J10: 0 - 3.999 kg
A11: CÁSCARA DE NARANJA | B11: CÁSCARA DE NARANJA | C11: 4 | D11: 7.999 | E11: 433.74 | F11: 560 | G11: 126.26 | H11: 22.546429 | I11: 29.109605 | J11: 4 - 7.999 kg
A12: CÁSCARA DE NARANJA | B12: CÁSCARA DE NARANJA | C12: 8 | D12: 19.999 | E12: 423.54 | F12: 540 | G12: 116.46 | H12: 21.566667 | I12: 27.496813 | J12: 8 - 19.999 kg
A13: CÁSCARA DE NARANJA | B13: CÁSCARA DE NARANJA | C13: 20 | E13: 413.8 | F13: 520 | G13: 106.2 | H13: 20.423077 | I13: 25.664572 | J13: + 20 kg
A14: EPO-DEEP | B14: EPO-DEEP TRANSPARENTE | C14: 0 | D14: 4.299 | E14: 461.88 | F14: 560 | G14: 98.12 | H14: 17.521429 | I14: 21.243613 | J14: 0 - 4.299 kg
A15: EPO-DEEP | B15: EPO-DEEP TRANSPARENTE | C15: 4.3 | D15: 7.099 | E15: 437.44 | F15: 540 | G15: 102.56 | H15: 18.992593 | I15: 23.445501 | J15: 4.3 - 7.099 kg
A16: EPO-DEEP | B16: EPO-DEEP TRANSPARENTE | C16: 7.1 | D16: 16.999 | E16: 424.71 | F16: 520 | G16: 95.29 | H16: 18.325 | I16: 22.436486 | J16: 7.1 - 16.999 kg
A17: EPO-DEEP | B17: EPO-DEEP TRANSPARENTE | C17: 17 | E17: 389.43 | F17: 500 | G17: 110.57 | H17: 22.114 | I17: 28.392779 | J17: + 17 kg
A18: EPO-DEEP ULTRA | B18: EPO-DEEP ULTRA (A Y B) TRANSPARENTE | C18: 0 | D18: 6.699 | E18: 392.24 | F18: 480 | G18: 87.76 | H18: 18.283333 | I18: 22.374057 | J18: 0 - 6.699 kg
A19: EPO-DEEP ULTRA | B19: EPO-DEEP ULTRA (A Y B) TRANSPARENTE | C19: 6.7 | D19: 13.299 | E19: 373.55 | F19: 460 | G19: 86.45 | H19: 18.793478 | I19: 23.142819 | J19: 6.7 - 13.299 kg
A20: EPO-DEEP ULTRA | B20: EPO-DEEP ULTRA (A Y B) TRANSPARENTE | C20: 13.3 | D20: 23.999 | E20: 355.77 | F20: 440 | G20: 84.23 | H20: 19.143182 | I20: 23.675408 | J20: 13.3 - 23.999 kg
A21: EPO-DEEP ULTRA | B21: EPO-DEEP ULTRA (A Y B) TRANSPARENTE | C21: 24 | E21: 325.58 | F21: 420 | G21: 94.42 | H21: 22.480952 | I21: 29.000553 | J21: + 24 kg
A22: EPO-FAST | B22: EPO-FAST (A Y B) TRANSPARENTE | C22: 0 | D22: 5.999 | E22: 392.24 | F22: 480 | G22: 87.76 | H22: 18.283333 | I22: 22.374057 | J22: 0 - 5.999 kg
A23: EPO-FAST | B23: EPO-FAST (A Y B) TRANSPARENTE | C23: 6 | D23: 9.999 | E23: 373.55 | F23: 460 | G23: 86.45 | H23: 18.793478 | I23: 23.142819 | J23: 6 - 9.999 kg
A24: EPO-FAST | B24: EPO-FAST (A Y B) TRANSPARENTE | C24: 10 | D24: 18.999 | E24: 355.77 | F24: 440 | G24: 84.23 | H24: 19.143182 | I24: 23.675408 | J24: 10 - 18.999 kg
A25: EPO-FAST | B25: EPO-FAST (A Y B) TRANSPARENTE | C25: 19 | E25: 325.58 | F25: 420 | G25: 94.42 | H25: 22.480952 | I25: 29.000553 | J25: + 19 kg
A26: EPOXY-HOJUELA (1 color) | B26: EPOXY-HOJUELA (1 color) | C26: 0 | D26: 59.999 | E26: 182.7 | F26: 205 | G26: 22.3 | H26: 10.878049 | I26: 12.205802 | J26: 0 - 59.999 kg
A27: EPOXY-HOJUELA (1 color) | B27: EPOXY-HOJUELA (1 color) | C27: 60 | E27: 182.7 | F27: 200 | G27: 17.3 | H27: 8.65 | I27: 9.469075 | J27: + 60 kg
A28: EPOXY-HOJUELA (combinación) | B28: EPOXY-HOJUELA (combinación) | C28: 0 | D28: 59.999 | E28: 214.5 | F28: 235 | G28: 20.5 | H28: 8.7234043 | I28: 9.5571096 | J28: 0 - 59.999 kg
A29: EPOXY-HOJUELA (combinación) | B29: EPOXY-HOJUELA (combinación) | C29: 60 | E29: 214.5 | F29: 230 | G29: 15.5 | H29: 6.7391304 | I29: 7.2261072 | J29: + 60 kg
A30: EPOXY CUARZO | B30: EPOXY CUARZO | C30: 0 | D30: 59.999 | E30: 29.34 | F30: 35 | G30: 5.66 | H30: 16.171429 | I30: 19.29107 | J30: 0 - 59.999 kg
A31: EPOXY CUARZO | B31: EPOXY CUARZO | C31: 60 | E31: 29.34 | F31: 30 | G31: 0.66 | H31: 2.2 | I31: 2.2494888 | J31: + 60 kg
A32: POLIURETANO | B32: POLIURETANO (A Y B) TRANSPARENTE | C32: 0 | D32: 4.999 | E32: 422.11 | F32: 460 | G32: 37.89 | H32: 8.236957 | I32: 8.976333 | J32: 0 - 4.999 kg
A33: POLIURETANO | B33: POLIURETANO (A Y B) TRANSPARENTE | C33: 5 | D33: 9.999 | E33: 395.02 | F33: 450 | G33: 54.98 | H33: 12.217778 | I33: 13.918283 | J33: 5 - 9.999 kg
A34: POLIURETANO | B34: POLIURETANO (A Y B) TRANSPARENTE | C34: 10 | D34: 19.999 | E34: 382.8 | F34: 440 | G34: 57.2 | H34: 13 | I34: 14.942529 | J34: 10 - 19.999 kg
A35: POLIURETANO | B35: POLIURETANO (A Y B) TRANSPARENTE | C35: 20 | E35: 369.09 | F35: 430 | G35: 60.91 | H35: 14.165116 | I35: 16.50275 | J35: + 20 kg
A36: ESTUCO VENECIANO | B36: ESTUCO VENECIANO | C36: 1 | D36: 3.999 | E36: 400 | F36: 480 | G36: 80 | H36: 16.666667 | I36: 20 | J36: 1 - 3.999 kg
A37: ESTUCO VENECIANO | B37: ESTUCO VENECIANO | C37: 4 | D37: 18.999 | E37: 380 | F37: 460 | G37: 80 | H37: 17.391304 | I37: 21.052632 | J37: 4 - 18.999 kg
A38: ESTUCO VENECIANO | B38: ESTUCO VENECIANO | C38: 19 | E38: 361 | F38: 440 | G38: 79 | H38: 17.954545 | I38: 21.883657 | J38: + 19 kg
A39: GRANO WALL | B39: GRANO WALL | C39: 4 | D39: 18.999 | E39: 231.58 | F39: 275 | G39: 43.42 | H39: 15.789091 | I39: 18.74946 | J39: 4 - 18.999 kg
A40: GRANO WALL | B40: GRANO WALL | C40: 19 | E40: 182.83 | F40: 225 | G40: 42.17 | H40: 18.742222 | I40: 23.065142 | J40: + 19 kg
